setup.py
doifinder/__init__.py
doifinder/doifinder.py
doifinder.egg-info/PKG-INFO
doifinder.egg-info/SOURCES.txt
doifinder.egg-info/dependency_links.txt
doifinder.egg-info/top_level.txt