Metadata-Version: 1.0
Name: doifinder
Version: 0.8
Summary: Python Distribution Utilitie to retrive a DOI number from Crossref, according to a given metadata
Home-page: http://www.python.org/sigs/distutils-sig/
Author: Fabio Batalha
Author-email: fabio.batalha@scielo.org
License: BSD License
Platform: UNKNOWN
Classifier: Development Status :: 4 - Beta
Classifier: Intended Audience :: Developers
Classifier: Programming Language :: Python
Classifier: Topic :: Software Development :: Libraries :: Python Modules
